modpath/__init__.py
modpath/__main__.py
modpath/cli.py
modpath/dtypes.py
modpath/errors.py
modpath/funcs.py
modpath-0.0.2.dist-info/AUTHORS
modpath-0.0.2.dist-info/LICENSE
modpath-0.0.2.dist-info/METADATA
modpath-0.0.2.dist-info/WHEEL
modpath-0.0.2.dist-info/entry_points.txt
modpath-0.0.2.dist-info/pbr.json
modpath-0.0.2.dist-info/top_level.txt
modpath-0.0.2.dist-info/RECORD
